{
    "name": "Global Giving Collector Specification",
    "version": "0.01",
    "elements": [
        {
            "tag":"Story",
            "required": false,
            "type":"StoryElement"
        },
        {
            "tag":"Topic",
            "type":"Tag"
        },
        {
            "tag":"Organization",
            "type":"StoryElement"
        }
    ],
    "relations": [
        {
            "type": "Causes",
            "from": "Organization",
            "to":   "Story"
        },
        {
            "type": "Tags",
            "from": "Topic",
            "to":   "Story"
        }
    ]
}
